metaidigitcv/__init__.py
metaidigitcv/main.py
metaidigitcv-0.1.16.dist-info/METADATA
metaidigitcv-0.1.16.dist-info/WHEEL
metaidigitcv-0.1.16.dist-info/entry_points.txt
metaidigitcv-0.1.16.dist-info/top_level.txt
metaidigitcv-0.1.16.dist-info/RECORD
