Metadata-Version: 2.2
Name: metaidigitcv
Version: 0.1.16
Summary: computer vision and machine learning library
Author: SUHAL SAMAD
Author-email: samadsuhal@gmail.com
Classifier: Programming Language :: Python :: 3
Classifier: License :: OSI Approved :: MIT License
Classifier: Operating System :: OS Independent
Requires-Python: >=3.10
Dynamic: author
Dynamic: author-email
Dynamic: classifier
Dynamic: description
Dynamic: description-content-type
Dynamic: requires-python
Dynamic: summary
